leetcodetest/__init__.py
leetcodetest/lib.py
leetcodetest-0.0.1.dist-info/METADATA
leetcodetest-0.0.1.dist-info/WHEEL
leetcodetest-0.0.1.dist-info/top_level.txt
leetcodetest-0.0.1.dist-info/RECORD
