Metadata-Version: 2.1
Name: leetcodetest
Version: 0.0.1
Summary: A simple leetcode testing utility.
Home-page: https://github.com/Asmeili/LeetcodeTest
Author: Asmeili
Project-URL: Bug Reports, https://github.com/Asmeili/LeetcodeTest/issues
Project-URL: Source, https://github.com/Asmeili/LeetcodeTest
Keywords: leetcode
Classifier: Development Status :: 3 - Alpha
Classifier: Intended Audience :: Developers
Classifier: Programming Language :: Python :: 3
Classifier: Programming Language :: Python :: 3.7
Classifier: Programming Language :: Python :: 3.8
Classifier: Programming Language :: Python :: 3.9
Classifier: Programming Language :: Python :: 3.10
Classifier: Programming Language :: Python :: 3 :: Only
Requires-Python: >=3.7, <4
